{
	"components": {
		"content" : [{
			"path": "partials/top-section.htm"
		}, {
			"path": "partials/bottom-section.htm"
		}, {
			"path": "partials/section-nodeatlas.htm"
		}, {
			"path": "partials/presentation.htm",
			"variations": {
				"components": {
					"content" : [{
						"path": "partials/header.htm"
					}, {
						"path": "partials/footer.htm"
					}]
				}
			}
		}]
	},
	"titlePage": "NodeAtlas, le framework JavaScript MVC par Bruno Lesieur",
	"description": "Venez découvrir mon framework au petit oignons spécialement designé pour les développeurs Front-end et JavaScript qui se soucis du SEO et du W3C !",
	"opened": {
		"main": "to top",
		"bepo": "",
		"offers": "",
		"book": "",
		"website": "",
		"blog": "",
		"front-end": "",
		"unknown-top": "",
		"unknown-bottom": "",
		"websites": "",
		"skills": "",
		"contact-me": "",
		"about-me": "",
		"nodeatlas": "open",
		"games": ""
	}
}